necbol/__init__.py
necbol/analyser.py
necbol/components.py
necbol/modeller.py
necbol/optimisers.py
necbol/visualiser.py
necbol-3.2.3.dist-info/licenses/LICENSE
necbol-3.2.3.dist-info/METADATA
necbol-3.2.3.dist-info/WHEEL
necbol-3.2.3.dist-info/top_level.txt
necbol-3.2.3.dist-info/RECORD
