Metadata-Version: 2.4
Name: necbol
Version: 3.2.3
Summary: A plain language Python wrapper for NEC
Author-email: G1OJS <g1ojs@yahoo.com>
License-Expression: MIT
Project-URL: Homepage, https://github.com/G1OJS/NECBOL
Project-URL: Issues, https://github.com/G1OJS/NECBOL/issues
Keywords: nec,antenna,wire editor,3D,electromagnetics,ham radio,radio,optimisation
Classifier: Programming Language :: Python :: 3
Classifier: Operating System :: OS Independent
Classifier: Development Status :: 5 - Production/Stable
Classifier: Intended Audience :: End Users/Desktop
Classifier: Intended Audience :: Science/Research
Classifier: Intended Audience :: Telecommunications Industry
Classifier: Topic :: Scientific/Engineering :: Physics
Classifier: Topic :: Scientific/Engineering :: Visualization
Requires-Python: >=3.8
License-File: LICENSE
Requires-Dist: numpy>=1.24.0
Requires-Dist: matplotlib
Dynamic: license-file
